Workbook

Sheet SIMULADOR
B2: FII INVEST — SIMULADOR DE PATRIMÔNIO E DIVIDENDOS
B5: CONFIGURAÇÕES DO INVESTIMENTO | H5: CONFIGURAÇÕES FINANCEIRAS
B7: Aporte Mensal (R$) | F7: 200 | H7: Salário Mensal (R$) | L7: 3000
B8: Prazo do Investimento (anos) | F8: 5 | H8: Percentual Sugerido de Aporte | L8: 30%
B9: Taxa de Rendimento Mensal (%) | F9: 1,079% | H9: Aporte Mensal Sugerido (R$) | L9: =L7*L8 -> 900
B11: Patrimônio Acumulado (R$) | F11: =FV(taxa_mensal,F8*12,-aporte,0,0) -> 16755.383 | H11: Perfil do Investidor | L11: Agressivo
B12: Dividendos Mensais Estimados (R$) | F12: =F11*0.6% -> 100.5323
B15: SIMULAÇÃO DE CENÁRIOS | H15: DISTRIBUIÇÃO DOS INVESTIMENTOS
B17: Prazo (anos) | D17: Patrimônio Projetado (R$) | F17: Dividendos Mensais (R$ | H17: Tipo de FII | J17: Percentual (%) | L17: Valor do Aporte (R$)
B18: 2 | D18: =FV(taxa_mensal,B18*12,-aporte,0,0) -> 5445.5255 | F18: =D18*0.6% -> 32.673153 | H18: Papel | J18: =VLOOKUP($L$11&"_"&H18,PERFIS_FII!$A$2:$D$21,4,0) -> 0.15 | L18: =aporte*J18 -> 30
B19: 5 | D19: =FV(taxa_mensal,B19*12,-aporte,0,0) -> 16755.383 | F19: =D19*0.6% -> 100.5323 | H19: Tijolo | J19: =VLOOKUP($L$11&"_"&H19,PERFIS_FII!$A$2:$D$21,4,0) -> 0.2 | L19: =aporte*J19 -> 40
B20: 10 | D20: =FV(taxa_mensal,B20*12,-aporte,0,0) -> 48656.843 | F20: =D20*0.6% -> 291.94106 | H20: Híbridos | J20: =VLOOKUP($L$11&"_"&H20,PERFIS_FII!$A$2:$D$21,4,0) -> 0.15 | L20: =aporte*J20 -> 30
B21: 20 | D21: =FV(taxa_mensal,B21*12,-aporte,0,0) -> 225039.68 | F21: =D21*0.6% -> 1350.2381 | H21: FOFs | J21: =VLOOKUP($L$11&"_"&H21,PERFIS_FII!$A$2:$D$21,4,0) -> 0.1 | L21: =aporte*J21 -> 20
B22: 30 | D22: =FV(taxa_mensal,B22*12,-aporte,0,0) -> 864433.93 | F22: =D22*0.6% -> 5186.6036 | H22: Desenvolvimento | J22: =VLOOKUP($L$11&"_"&H22,PERFIS_FII!$A$2:$D$21,4,0) -> 0.25 | L22: =aporte*J22 -> 50
H23: Hotelaria | J23: =VLOOKUP($L$11&"_"&H23,PERFIS_FII!$A$2:$D$21,4,0) -> 0.15 | L23: =aporte*J23 -> 30
H24: Total | J24: =SUM(J18:J23) -> 1 | L24: =SUM(L18:L23) -> 200

Sheet PERFIS_FII
A1: Chave | B1: Perfil do Investidor | C1: Tipo de FII | D1: Percentual de Alocação
A2: =B2&"_"&C2 -> Conservador_Papel | B2: Conservador | C2: Papel | D2: 0.35
A3: =B3&"_"&C3 -> Conservador_Tijolo | B3: Conservador | C3: Tijolo | D3: 0.3
A4: =B4&"_"&C4 -> Conservador_Híbridos | B4: Conservador | C4: Híbridos | D4: 0.2
A5: =B5&"_"&C5 -> Conservador_FOFs | B5: Conservador | C5: FOFs | D5: 0.1
A6: =B6&"_"&C6 -> Conservador_Desenvolvimento | B6: Conservador | C6: Desenvolvimento | D6: 0.03
A7: =B7&"_"&C7 -> Conservador_Hotelaria | B7: Conservador | C7: Hotelaria | D7: 0.02
C8: Total | D8: =SUM(D2:D7) -> 1
A9: =B9&"_"&C9 -> Moderado_Papel | B9: Moderado | C9: Papel | D9: 0.25
A10: =B10&"_"&C10 -> Moderado_Tijolo | B10: Moderado | C10: Tijolo | D10: 0.3
A11: =B11&"_"&C11 -> Moderado_Híbridos | B11: Moderado | C11: Híbridos | D11: 0.2
A12: =B12&"_"&C12 -> Moderado_FOFs | B12: Moderado | C12: FOFs | D12: 0.15
A13: =B13&"_"&C13 -> Moderado_Desenvolvimento | B13: Moderado | C13: Desenvolvimento | D13: 0.05
A14: =B14&"_"&C14 -> Moderado_Hotelaria | B14: Moderado | C14: Hotelaria | D14: 0.05
C15: Total | D15: =SUM(D9:D14) -> 1
A16: =B16&"_"&C16 -> Agressivo_Papel | B16: Agressivo | C16: Papel | D16: 0.15
A17: =B17&"_"&C17 -> Agressivo_Tijolo | B17: Agressivo | C17: Tijolo | D17: 0.2
A18: =B18&"_"&C18 -> Agressivo_Híbridos | B18: Agressivo | C18: Híbridos | D18: 0.15
A19: =B19&"_"&C19 -> Agressivo_FOFs | B19: Agressivo | C19: FOFs | D19: 0.1
A20: =B20&"_"&C20 -> Agressivo_Desenvolvimento | B20: Agressivo | C20: Desenvolvimento | D20: 0.25
A21: =B21&"_"&C21 -> Agressivo_Hotelaria | B21: Agressivo | C21: Hotelaria | D21: 0.15
C22: Total | D22: =SUM(D16:D21) -> 1
